periodic_table/__init__.py
periodic_table/ptable.py
ravi_periodic_table-0.1.dist-info/DESCRIPTION.rst
ravi_periodic_table-0.1.dist-info/METADATA
ravi_periodic_table-0.1.dist-info/RECORD
ravi_periodic_table-0.1.dist-info/WHEEL
ravi_periodic_table-0.1.dist-info/metadata.json
ravi_periodic_table-0.1.dist-info/top_level.txt
