Metadata-Version: 2.0
Name: ravi-periodic-table
Version: 0.1
Summary: chemistry symbols and name
Home-page: http://github.com/ravigadila/ravi_periodic_table
Author: ravigadila
Author-email: ravi@micropyramid.com
License: MIT
Platform: UNKNOWN
